[
    {
        "Indice": 1,
        "R": 34,
        "G": 33,
        "B": 34,
        "Clase": 1
    },
    {
        "Indice": 2,
        "R": 43,
        "G": 43,
        "B": 43,
        "Clase": 1
    },
    {
        "Indice": 3,
        "R": 37,
        "G": 34,
        "B": 37,
        "Clase": 1
    },
    {
        "Indice": 4,
        "R": 41,
        "G": 39,
        "B": 40,
        "Clase": 1
    },
    {
        "Indice": 5,
        "R": 46,
        "G": 44,
        "B": 45,
        "Clase": 1
    },
    {
        "Indice": 6,
        "R": 45,
        "G": 45,
        "B": 45,
        "Clase": 1
    },
    {
        "Indice": 7,
        "R": 47,
        "G": 45,
        "B": 46,
        "Clase": 1
    },
    {
        "Indice": 8,
        "R": 44,
        "G": 42,
        "B": 43,
        "Clase": 1
    },
    {
        "Indice": 9,
        "R": 35,
        "G": 34,
        "B": 35,
        "Clase": 1
    },
    {
        "Indice": 10,
        "R": 30,
        "G": 27,
        "B": 30,
        "Clase": 1
    },
    {
        "Indice": 11,
        "R": 32,
        "G": 29,
        "B": 32,
        "Clase": 1
    },
    {
        "Indice": 12,
        "R": 45,
        "G": 43,
        "B": 44,
        "Clase": 1
    },
    {
        "Indice": 13,
        "R": 45,
        "G": 43,
        "B": 44,
        "Clase": 1
    },
    {
        "Indice": 14,
        "R": 52,
        "G": 50,
        "B": 51,
        "Clase": 1
    },
    {
        "Indice": 15,
        "R": 48,
        "G": 46,
        "B": 47,
        "Clase": 1
    },
    {
        "Indice": 16,
        "R": 48,
        "G": 46,
        "B": 47,
        "Clase": 1
    },
    {
        "Indice": 17,
        "R": 45,
        "G": 42,
        "B": 44,
        "Clase": 1
    },
    {
        "Indice": 18,
        "R": 4,
        "G": 4,
        "B": 4,
        "Clase": 1
    },
    {
        "Indice": 19,
        "R": 2,
        "G": 0,
        "B": 1,
        "Clase": 1
    },
    {
        "Indice": 20,
        "R": 210,
        "G": 210,
        "B": 208,
        "Clase": 1
    },
    {
        "Indice": 21,
        "R": 174,
        "G": 174,
        "B": 172,
        "Clase": 1
    }
]